Metadata-Version: 2.1
Name: crgoauth
Version: 0.0.1.dev6
Summary: Cloudreach implementation of Google SignIn OAuth
Home-page: https://github.com/nikolay-tonev/crgoauth
Author: Cloudreach
Author-email: nikolay.tonev@cloudreach.com
Project-URL: Bug Tracker, https://github.com/nikolay-tonev/crgoauth/issues
Classifier: Development Status :: 2 - Pre-Alpha
Classifier: Environment :: MacOS X
Requires-Python: >=3.6
